{
  "events": [
    {
      "id": 1,
      "name": "Codaisseur Demo Night",
      "date": "30-07-2020",
      "description": "This is the best demo night you have ever seen. It's a-m-a-z-i-n-g. Seriously. Lets make a dent in the universe."
    },
    {
      "name": "",
      "date": "",
      "description": "",
      "id": 7
    },
    {
      "name": "",
      "date": "",
      "description": "",
      "id": 9
    },
    {
      "name": "",
      "date": "",
      "description": "",
      "id": 10
    }
  ],
  "comments": [
    {
      "id": 1,
      "author": "Eric",
      "body": "After one look at this planet any visitor from outer space would say “I WANT TO SEE THE MANAGER.”",
      "eventId": 1
    },
    {
      "id": 3,
      "author": "Billy",
      "body": "I'm always relieved when someone is delivering a eulogy and I realise I'm listening to it.",
      "eventId": 1
    },
    {
      "id": 4,
      "author": "Pete",
      "body": "A good lawyer knows the law; a clever one takes the judge to lunch.",
      "eventId": 1
    }
  ]
}